{
  "context-menu": {
    "atom-text-editor": [
      {
        "label": "Gatrix",
        "submenu": [
          {
            "label": "Toggle Encryption",
            "command": "gatrix:toggle"
          }
        ]
      }
    ]
  },
  "menu": [
    {
      "label": "Packages",
      "submenu": [
        {
          "label": "Gatrix",
          "submenu": [
            {
              "label": "Toggle Encryption",
              "command": "gatrix:toggle"
            }
          ]
        }
      ]
    }
  ]
}
